poetry_youtube/__init__.py
poetry_youtube/main.py
poetry_youtube-0.1.0.dist-info/METADATA
poetry_youtube-0.1.0.dist-info/WHEEL
poetry_youtube-0.1.0.dist-info/RECORD
